pdcd/__init__.py
pdcd/cli.py
pdcd/config.py
pdcd/connectors.py
pdcd/external.py
pdcd/files.py
pdcd/jobs.py
pdcd/log.py
pdcd/routines.py
pdcd/settings.py
pdcd/shellcode.py
pdcd/utils.py
pdcd-1.2.1.dist-info/LICENSE
pdcd-1.2.1.dist-info/METADATA
pdcd-1.2.1.dist-info/WHEEL
pdcd-1.2.1.dist-info/entry_points.txt
pdcd-1.2.1.dist-info/RECORD
