Metadata-Version: 2.1
Name: pdcd
Version: 1.2.1
Summary: Tool that orchestrates executing Docker containers to build payloads
License: MIT
Author: 2XXE
Author-email: root@example.com
Requires-Python: >=3.8,<4.0
Classifier: License :: OSI Approved :: MIT License
Classifier: Programming Language :: Python :: 3
Classifier: Programming Language :: Python :: 3.8
Classifier: Programming Language :: Python :: 3.9
Classifier: Programming Language :: Python :: 3.10
Classifier: Programming Language :: Python :: 3.11
Requires-Dist: boto3 (>=1.35.47,<2.0.0)
Requires-Dist: click (>=8.1.7,<9.0.0)
Requires-Dist: desert (>=2022.9.22,<2023.0.0)
Requires-Dist: docker (>=7.1.0,<8.0.0)
Requires-Dist: impacket (>=0.12.0,<0.13.0)
Requires-Dist: mythic (>=0.2.5,<0.3.0)
Requires-Dist: pydantic-settings (>=2.6.0,<3.0.0)
Requires-Dist: pyyaml (>=6.0.2,<7.0.0)
